aiokevoplus/__init__.py
aiokevoplus/const.py
aiokevoplus-4.3.2.dist-info/LICENSE
aiokevoplus-4.3.2.dist-info/METADATA
aiokevoplus-4.3.2.dist-info/WHEEL
aiokevoplus-4.3.2.dist-info/top_level.txt
aiokevoplus-4.3.2.dist-info/RECORD
