Metadata-Version: 2.1
Name: aiokevoplus
Version: 4.3.2
Summary: Control Kwikset Kevo locks
Home-page: https://github.com/dcmeglio/pykevoplus
Author: Dominick Meglio
Author-email: dmeglio@gmail.com
License: MIT
Keywords: kevo kwikset
License-File: LICENSE
Requires-Dist: httpx
Requires-Dist: pkce
Requires-Dist: PyJWT
Requires-Dist: websockets
